rdbgen_rs-0.1.1.dist-info/METADATA
rdbgen_rs-0.1.1.dist-info/WHEEL
rdbgen_rs-0.1.1.dist-info/licenses/LICENSE
rdbgen_rs/py.typed
rdbgen_rs/_version.py
rdbgen_rs/_rdbgen_rs.pyi
rdbgen_rs/__init__.py
rdbgen_rs/_rdbgen_rs.cpython-310-aarch64-linux-gnu.so
rdbgen_rs-0.1.1.dist-info/RECORD
